README.rst
pypez.py
setup.py
pypez.egg-info/PKG-INFO
pypez.egg-info/SOURCES.txt
pypez.egg-info/dependency_links.txt
pypez.egg-info/pbr.json
pypez.egg-info/requires.txt
pypez.egg-info/top_level.txt