Metadata-Version: 1.1
Name: pypez
Version: 0.1.5
Summary: simple pipelines in python
Home-page: https://github.com/bw2/pypez
Author: Ben
Author-email: ben.weisburd@gmail.com
License: MIT
Keywords: pype,unix,pipeline,pipelines,parallelization,SGE,LSF
Platform: UNKNOWN
Classifier: Development Status :: 4 - Beta
Classifier: Intended Audience :: Developers
Classifier: License :: OSI Approved :: MIT License
Classifier: Natural Language :: English
Classifier: Programming Language :: Python :: 2
Classifier: Programming Language :: Python :: 2.7
Classifier: Programming Language :: Python :: 3
Classifier: Programming Language :: Python :: 3.2
Classifier: Programming Language :: Python :: 3.3
Classifier: Programming Language :: Python :: 3.4
Classifier: Programming Language :: Python :: 3.5
Classifier: Programming Language :: Python :: Implementation :: CPython
Classifier: Programming Language :: Python :: Implementation :: PyPy
